{"trial_id": "4", "hyperparameters": {"space": [{"class_name": "Int", "config": {"name": "user_embedding_dim", "default": null, "conditions": [], "min_value": 32, "max_value": 128, "step": 32, "sampling": "linear"}}, {"class_name": "Int", "config": {"name": "item_embedding_dim", "default": null, "conditions": [], "min_value": 32, "max_value": 128, "step": 32, "sampling": "linear"}}, {"class_name": "Int", "config": {"name": "age_embedding_dim", "default": null, "conditions": [], "min_value": 32, "max_value": 128, "step": 32, "sampling": "linear"}}, {"class_name": "Int", "config": {"name": "occupation_embedding_dim", "default": null, "conditions": [], "min_value": 32, "max_value": 128, "step": 32, "sampling": "linear"}}, {"class_name": "Int", "config": {"name": "gender_embedding_dim", "default": null, "conditions": [], "min_value": 32, "max_value": 128, "step": 32, "sampling": "linear"}}, {"class_name": "Int", "config": {"name": "dense1_units", "default": null, "conditions": [], "min_value": 64, "max_value": 512, "step": 64, "sampling": "linear"}}, {"class_name": "Int", "config": {"name": "dense2_units", "default": null, "conditions": [], "min_value": 32, "max_value": 256, "step": 32, "sampling": "linear"}}, {"class_name": "Int", "config": {"name": "dense3_units", "default": null, "conditions": [], "min_value": 16, "max_value": 128, "step": 16, "sampling": "linear"}}, {"class_name": "Float", "config": {"name": "dropout1", "default": 0.2, "conditions": [], "min_value": 0.2, "max_value": 0.5, "step": 0.1, "sampling": "linear"}}], "values": {"user_embedding_dim": 96, "item_embedding_dim": 64, "age_embedding_dim": 32, "occupation_embedding_dim": 64, "gender_embedding_dim": 32, "dense1_units": 320, "dense2_units": 256, "dense3_units": 16, "dropout1": 0.4}}, "metrics": {"metrics": {"loss": {"direction": "min", "observations": [{"value": [0.6188128789265951], "step": 9}]}, "mae": {"direction": "min", "observations": [{"value": [0.6166960597038269], "step": 9}]}, "val_loss": {"direction": "min", "observations": [{"value": [0.4960285524527232], "step": 9}]}, "val_mae": {"direction": "min", "observations": [{"value": [0.545649786790212], "step": 9}]}}}, "score": 0.545649786790212, "best_step": 9, "status": "COMPLETED", "message": null}